seqtok.py
seqtok-0.1.0a1.dist-info/licenses/LICENSE
seqtok-0.1.0a1.dist-info/METADATA
seqtok-0.1.0a1.dist-info/WHEEL
seqtok-0.1.0a1.dist-info/top_level.txt
seqtok-0.1.0a1.dist-info/RECORD
