Metadata-Version: 2.4
Name: seqtok
Version: 0.1.0a1
Summary: A Python implementation mimicking C's `strtok()` behavior for generic sequences, but without global state.
Author-email: Jifeng Wu <jifengwu2k@gmail.com>
License-Expression: MIT
Project-URL: Homepage, https://github.com/jifengwu2k/seqtok
Project-URL: Bug Tracker, https://github.com/jifengwu2k/seqtok/issues
Classifier: Programming Language :: Python :: 2
Classifier: Programming Language :: Python :: 3
Classifier: Operating System :: OS Independent
Requires-Python: >=2
License-File: LICENSE
Requires-Dist: cowlist
Requires-Dist: typing; python_version < "3.5"
Dynamic: license-file
